<?xml version="1.0" encoding="UTF-8"?>
<con:soapui-project id="1ac5ce10-d01b-411d-b993-d1a29ee95c45" activeEnvironment="Default" name="speller.yandex" soapui-version="5.6.0" abortOnError="false" runType="SEQUENTIAL" xmlns:con="http://eviware.com/soapui/config"><con:settings/><con:interface xsi:type="con:WsdlInterface" id="7568de91-179b-4844-a71a-a834c7220d2f" wsaVersion="NONE" name="SpellServiceSoap12" type="wsdl" bindingName="{http://speller.yandex.net/services/spellservice}SpellServiceSoap12" soapVersion="1_2" anonymous="optional" definition="https://speller.yandex.net/services/spellservice?WSDL" xmlns:xsi="http://www.w3.org/2001/XMLSchema-instance"><con:settings/><con:definitionCache type="TEXT" rootPart="https://speller.yandex.net/services/spellservice?WSDL"><con:part><con:url>https://speller.yandex.net/services/spellservice?WSDL</con:url><con:content><![CDATA[<wsdl:definitions targetNamespace="http://speller.yandex.net/services/spellservice" xmlns:soap="http://schemas.xmlsoap.org/wsdl/soap/" xmlns:tns="http://speller.yandex.net/services/spellservice" xmlns:s="http://www.w3.org/2001/XMLSchema" xmlns:soap12="http://schemas.xmlsoap.org/wsdl/soap12/" xmlns:http="http://schemas.xmlsoap.org/wsdl/http/" xmlns:wsdl="http://schemas.xmlsoap.org/wsdl/">
  <wsdl:types>
    <s:schema elementFormDefault="qualified" targetNamespace="http://speller.yandex.net/services/spellservice">
      <s:element name="CheckTextRequest">
        <s:complexType>
          <s:sequence>
            <s:element minOccurs="1" maxOccurs="1" name="text" type="s:string"/>
          </s:sequence>
          <s:attribute name="lang" type="s:string"/>
          <s:attribute name="options" type="s:int" use="optional" default="0"/>
          <s:attribute name="format" type="s:string" use="optional" default=""/>
        </s:complexType>
      </s:element>
      <s:element name="CheckTextResponse">
        <s:complexType>
          <s:sequence>
            <s:element minOccurs="1" maxOccurs="1" name="SpellResult" type="tns:SpellResult"/>
          </s:sequence>
        </s:complexType>
      </s:element>
      <s:complexType name="SpellResult">
        <s:sequence>
          <s:element minOccurs="0" maxOccurs="unbounded" name="error" type="tns:SpellError"/>
        </s:sequence>
      </s:complexType>
      <s:complexType name="SpellError">
        <s:sequence>
          <s:element minOccurs="1" maxOccurs="1" name="word" type="s:string"/>
          <s:element minOccurs="0" maxOccurs="unbounded" name="s" type="s:string"/>
        </s:sequence>
        <s:attribute name="code" type="s:int" use="required"/>
        <s:attribute name="pos" type="s:int" use="required"/>
        <s:attribute name="row" type="s:int" use="required"/>
        <s:attribute name="col" type="s:int" use="required"/>
        <s:attribute name="len" type="s:int" use="required"/>
      </s:complexType>
      <s:element name="CheckTextsRequest">
        <s:complexType>
          <s:sequence>
            <s:element minOccurs="0" maxOccurs="unbounded" name="text" type="s:string"/>
          </s:sequence>
          <s:attribute name="lang" type="s:string"/>
          <s:attribute name="options" type="s:int" use="optional" default="0"/>
          <s:attribute name="format" type="s:string" use="optional" default=""/>
        </s:complexType>
      </s:element>
      <s:element name="CheckTextsResponse">
        <s:complexType>
          <s:sequence>
            <s:element minOccurs="1" maxOccurs="1" name="ArrayOfSpellResult" type="tns:ArrayOfSpellResult"/>
          </s:sequence>
        </s:complexType>
      </s:element>
      <s:complexType name="ArrayOfSpellResult">
        <s:sequence>
          <s:element minOccurs="0" maxOccurs="unbounded" name="SpellResult" type="tns:SpellResult"/>
        </s:sequence>
      </s:complexType>
    </s:schema>
  </wsdl:types>
  <wsdl:message name="checkTextSoapIn">
    <wsdl:part name="parameters" element="tns:CheckTextRequest"/>
  </wsdl:message>
  <wsdl:message name="checkTextSoapOut">
    <wsdl:part name="parameters" element="tns:CheckTextResponse"/>
  </wsdl:message>
  <wsdl:message name="checkTextsSoapIn">
    <wsdl:part name="parameters" element="tns:CheckTextsRequest"/>
  </wsdl:message>
  <wsdl:message name="checkTextsSoapOut">
    <wsdl:part name="parameters" element="tns:CheckTextsResponse"/>
  </wsdl:message>
  <wsdl:portType name="SpellServiceSoap">
    <wsdl:operation name="checkText">
      <wsdl:input message="tns:checkTextSoapIn"/>
      <wsdl:output message="tns:checkTextSoapOut"/>
    </wsdl:operation>
    <wsdl:operation name="checkTexts">
      <wsdl:input message="tns:checkTextsSoapIn"/>
      <wsdl:output message="tns:checkTextsSoapOut"/>
    </wsdl:operation>
  </wsdl:portType>
  <wsdl:binding name="SpellServiceSoap" type="tns:SpellServiceSoap">
    <soap:binding transport="http://schemas.xmlsoap.org/soap/http"/>
    <wsdl:operation name="checkText">
      <soap:operation soapAction="http://speller.yandex.net/services/spellservice/checkText" style="document"/>
      <wsdl:input>
        <soap:body use="literal"/>
      </wsdl:input>
      <wsdl:output>
        <soap:body use="literal"/>
      </wsdl:output>
    </wsdl:operation>
    <wsdl:operation name="checkTexts">
      <soap:operation soapAction="http://speller.yandex.net/services/spellservice/checkTexts" style="document"/>
      <wsdl:input>
        <soap:body use="literal"/>
      </wsdl:input>
      <wsdl:output>
        <soap:body use="literal"/>
      </wsdl:output>
    </wsdl:operation>
  </wsdl:binding>
  <wsdl:binding name="SpellServiceSoap12" type="tns:SpellServiceSoap">
    <soap12:binding transport="http://schemas.xmlsoap.org/soap/http"/>
    <wsdl:operation name="checkText">
      <soap12:operation soapAction="http://speller.yandex.net/services/spellservice/checkText" style="document"/>
      <wsdl:input>
        <soap12:body use="literal"/>
      </wsdl:input>
      <wsdl:output>
        <soap12:body use="literal"/>
      </wsdl:output>
    </wsdl:operation>
    <wsdl:operation name="checkTexts">
      <soap12:operation soapAction="http://speller.yandex.net/services/spellservice/checkTexts" style="document"/>
      <wsdl:input>
        <soap12:body use="literal"/>
      </wsdl:input>
      <wsdl:output>
        <soap12:body use="literal"/>
      </wsdl:output>
    </wsdl:operation>
  </wsdl:binding>
  <wsdl:service name="SpellService">
    <wsdl:port name="SpellServiceSoap" binding="tns:SpellServiceSoap">
      <soap:address location="http://speller.yandex.net/services/spellservice"/>
    </wsdl:port>
    <wsdl:port name="SpellServiceSoap12" binding="tns:SpellServiceSoap12">
      <soap12:address location="http://speller.yandex.net/services/spellservice"/>
    </wsdl:port>
  </wsdl:service>
</wsdl:definitions>]]></con:content><con:type>http://schemas.xmlsoap.org/wsdl/</con:type></con:part></con:definitionCache><con:endpoints><con:endpoint>http://speller.yandex.net/services/spellservice</con:endpoint></con:endpoints><con:operation id="1efbb54d-ca29-4230-ba06-c447af41d769" isOneWay="false" action="http://speller.yandex.net/services/spellservice/checkText" name="checkText" bindingOperationName="checkText" type="Request-Response" inputName="" receivesAttachments="false" sendsAttachments="false" anonymous="optional"><con:settings/><con:call id="4bea3b9f-548c-41fe-8372-9869a2029607" name="Request 1"><con:settings/><con:encoding>UTF-8</con:encoding><con:endpoint>http://speller.yandex.net/services/spellservice</con:endpoint><con:request><![CDATA[<soap:Envelope xmlns:soap="http://www.w3.org/2003/05/soap-envelope" xmlns:spel="http://speller.yandex.net/services/spellservice">\r
   <soap:Header/>\r
   <soap:Body>\r
      <spel:CheckTextRequest lang="?" options="0" format="">\r
         <spel:text>?</spel:text>\r
      </spel:CheckTextRequest>\r
   </soap:Body>\r
</soap:Envelope>]]></con:request><con:wsaConfig mustUnderstand="NONE" version="200508" action="http://speller.yandex.net/services/spellservice/SpellServiceSoap/checkTextRequest"/></con:call></con:operation><con:operation id="61a0f724-cde5-42d9-8537-1baed570cce2" isOneWay="false" action="http://speller.yandex.net/services/spellservice/checkTexts" name="checkTexts" bindingOperationName="checkTexts" type="Request-Response" inputName="" receivesAttachments="false" sendsAttachments="false" anonymous="optional"><con:settings/><con:call id="af343ce1-f54f-4f64-bb27-284a0cfef525" name="Request 1"><con:settings><con:setting id="com.eviware.soapui.impl.wsdl.WsdlRequest@request-headers">&lt;xml-fragment/></con:setting></con:settings><con:encoding>UTF-8</con:encoding><con:endpoint>http://speller.yandex.net/services/spellservice</con:endpoint><con:request><![CDATA[<soap:Envelope xmlns:soap="http://www.w3.org/2003/05/soap-envelope" xmlns:spel="http://speller.yandex.net/services/spellservice">\r
   <soap:Header/>\r
   <soap:Body>\r
      <spel:CheckTextsRequest lang="ru" options="0" format="">\r
         <!--Zero or more repetitions:-->\r
         <spel:text> ключает в себя два метода, которые позволяют проверять правописани </spel:text>\r
      </spel:CheckTextsRequest>\r
   </soap:Body>\r
</soap:Envelope>]]></con:request><con:credentials><con:authType>No Authorization</con:authType></con:credentials><con:jmsConfig JMSDeliveryMode="PERSISTENT"/><con:jmsPropertyConfig/><con:wsaConfig mustUnderstand="NONE" version="200508" action="http://speller.yandex.net/services/spellservice/SpellServiceSoap/checkTextsRequest"/><con:wsrmConfig version="1.2"/></con:call></con:operation></con:interface><con:testSuite id="6e511886-6bc5-4d5e-8fe9-0fac8fc7a405" name="TestSuite 1"><con:settings/><con:runType>SEQUENTIAL</con:runType><con:testCase id="0882416f-9a02-405c-a298-d4ddfa9b3d9b" failOnError="true" failTestCaseOnErrors="true" keepSession="false" maxResults="0" name="TestCase 1" searchProperties="true"><con:settings/><con:testStep type="request" name="SOAP Request" id="9e33e7db-bf6a-4da2-8ed8-f6462ad1161e"><con:settings/><con:config xsi:type="con:RequestStep" xmlns:xsi="http://www.w3.org/2001/XMLSchema-instance"><con:interface>SpellServiceSoap12</con:interface><con:operation>checkTexts</con:operation><con:request name="SOAP Request" id="3ba5fe73-f45c-42b3-852f-3154295379b9"><con:settings><con:setting id="com.eviware.soapui.impl.wsdl.WsdlRequest@request-headers">&lt;xml-fragment/></con:setting></con:settings><con:encoding>UTF-8</con:encoding><con:endpoint>http://speller.yandex.net/services/spellservice</con:endpoint><con:request><![CDATA[<soap:Envelope xmlns:soap="http://www.w3.org/2003/05/soap-envelope" xmlns:spel="http://speller.yandex.net/services/spellservice">\r
   <soap:Header/>\r
   <soap:Body>\r
            <spel:CheckTextsRequest lang="ru,en"  options="8" format="">
                  <spel:text> включает в себя себя два метода, которые позволяют проверять правописани </spel:text>
                  <spel:text>TherE are are five types of schools in the US educational system. They are: kindergarten, elementary school, middle school, high school and private school.</spel:text>
      </spel:CheckTextsRequest >
   </soap:Body>\r
</soap:Envelope>]]></con:request><con:assertion type="SOAP Response" id="49a05206-f13a-46ce-b501-04c7ed1efff1"/><con:assertion type="Schema Compliance" id="5a649ad0-d5e5-4e92-a3fe-21626683377c"><con:configuration/></con:assertion><con:assertion type="XPath Match" id="930a3039-8d3b-4ce8-962f-a4779e12997c" name="S[1]"><con:configuration><path>declare namespace ns1='http://speller.yandex.net/services/spellservice';
declare namespace soap='http://www.w3.org/2003/05/soap-envelope';
//ns1:ArrayOfSpellResult/ns1:SpellResult[1]/ns1:error/ns1:s</path><content>правописание</content><allowWildcards>false</allowWildcards><ignoreNamspaceDifferences>false</ignoreNamspaceDifferences><ignoreComments>false</ignoreComments></con:configuration></con:assertion><con:assertion type="XPath Match" id="2622aaf0-10c2-4c81-be24-3974b9d9e265" name="S[2]"><con:configuration><path>declare namespace ns1='http://speller.yandex.net/services/spellservice';
declare namespace soap='http://www.w3.org/2003/05/soap-envelope';
//ns1:ArrayOfSpellResult/ns1:SpellResult[2]/ns1:error/ns1:s</path><content>There</content><allowWildcards>false</allowWildcards><ignoreNamspaceDifferences>false</ignoreNamspaceDifferences><ignoreComments>false</ignoreComments></con:configuration></con:assertion><con:assertion type="XPath Match" id="ed587439-4b61-4689-854a-0fa89215ed0b" name="code[1]"><con:configuration><path>declare namespace ns1='http://speller.yandex.net/services/spellservice';
declare namespace soap='http://www.w3.org/2003/05/soap-envelope';
//ns1:ArrayOfSpellResult/ns1:SpellResult[1]/ns1:error/@code</path><content>1</content><allowWildcards>false</allowWildcards><ignoreNamspaceDifferences>false</ignoreNamspaceDifferences><ignoreComments>false</ignoreComments></con:configuration></con:assertion><con:assertion type="XPath Match" id="719fdd75-24df-4175-b35d-5528b6157fb4" name="code[2]"><con:configuration><path>declare namespace ns1='http://speller.yandex.net/services/spellservice';
declare namespace soap='http://www.w3.org/2003/05/soap-envelope';
//ns1:ArrayOfSpellResult/ns1:SpellResult[2]/ns1:error/@code</path><content>3</content><allowWildcards>false</allowWildcards><ignoreNamspaceDifferences>false</ignoreNamspaceDifferences><ignoreComments>false</ignoreComments></con:configuration></con:assertion><con:assertion type="XPath Match" id="82247944-8fde-43cb-b2e0-64b741c7b5f5" name="code3"><con:configuration><path>declare namespace ns1='http://speller.yandex.net/services/spellservice';
declare namespace soap='http://www.w3.org/2003/05/soap-envelope';
//ns1:ArrayOfSpellResult/ns1:SpellResult[2]/ns1:error[2]/@code</path><content>2</content><allowWildcards>false</allowWildcards><ignoreNamspaceDifferences>false</ignoreNamspaceDifferences><ignoreComments>false</ignoreComments></con:configuration></con:assertion><con:assertion type="XPath Match" id="4555b6c6-66cc-4f6a-bbaa-3c27feb3f111" name="Word[code2]"><con:configuration><path>declare namespace ns1='http://speller.yandex.net/services/spellservice';
declare namespace soap='http://www.w3.org/2003/05/soap-envelope';
//ns1:ArrayOfSpellResult/ns1:SpellResult[2]/ns1:error[2]/ns1:word</path><content>are</content><allowWildcards>false</allowWildcards><ignoreNamspaceDifferences>false</ignoreNamspaceDifferences><ignoreComments>false</ignoreComments></con:configuration></con:assertion><con:credentials><con:authType>No Authorization</con:authType></con:credentials><con:jmsConfig JMSDeliveryMode="PERSISTENT"/><con:jmsPropertyConfig/><con:wsaConfig mustUnderstand="NONE" version="200508"/><con:wsrmConfig version="1.2"/></con:request></con:config></con:testStep><con:testStep type="request" name="SOAP Request 1" id="742d71d3-ba3a-497a-bcf2-874b02007649"><con:settings/><con:config xsi:type="con:RequestStep" xmlns:xsi="http://www.w3.org/2001/XMLSchema-instance"><con:interface>SpellServiceSoap12</con:interface><con:operation>checkTexts</con:operation><con:request name="SOAP Request 1" id="1dac8f11-5c35-4da2-825d-64494d76cfcf"><con:settings/><con:encoding>UTF-8</con:encoding><con:endpoint>http://speller.yandex.net/services/spellservice</con:endpoint><con:request><![CDATA[<soap:Envelope xmlns:soap="http://www.w3.org/2003/05/soap-envelope" xmlns:spel="http://speller.yandex.net/services/spellservice">\r
   <soap:Header/>\r
   <soap:Body>\r
      <spel:CheckTextsRequest/>\r
   </soap:Body>\r
</soap:Envelope>]]></con:request><con:assertion type="SOAP Response" id="753a01f6-f651-44d7-b848-9d9953656d83"/><con:assertion type="Schema Compliance" id="11293681-988b-4407-9dfd-68de08e6917b"><con:configuration/></con:assertion><con:credentials><con:authType>No Authorization</con:authType></con:credentials><con:jmsConfig JMSDeliveryMode="PERSISTENT"/><con:jmsPropertyConfig/><con:wsaConfig mustUnderstand="NONE" version="200508"/><con:wsrmConfig version="1.2"/></con:request></con:config></con:testStep><con:properties/></con:testCase><con:properties/></con:testSuite><con:properties/><con:wssContainer/><con:oAuth2ProfileContainer/><con:oAuth1ProfileContainer/></con:soapui-project>